bayesian_networks/__init__.py
bayesian_networks/approximate_inference.py
bayesian_networks/bayesian.py
bayesian_networks/enumeration.py
bayesian_networks-0.9.dist-info/METADATA
bayesian_networks-0.9.dist-info/WHEEL
bayesian_networks-0.9.dist-info/top_level.txt
bayesian_networks-0.9.dist-info/RECORD
