Metadata-Version: 2.1
Name: bayesian-networks
Version: 0.9
Summary: Implementation for bayesian network with Enumeration, Rejection Sampling and Likelihood Weighting
Home-page: https://github.com/bkbilly/bayesian_networks
Author: bkbilly
Author-email: bkbilly@hotmail.com
License: UNKNOWN
Platform: UNKNOWN
Classifier: Programming Language :: Python :: 3
Classifier: License :: OSI Approved :: MIT License
Classifier: Operating System :: OS Independent
Requires-Dist: pytz (>=2019.2)
Requires-Dist: matplotlib (>=3.0.3)
Requires-Dist: networkx (>=2.4)
